gs_xcom_backend/__init__.py
gs_xcom_backend/deferrer.py
gs_xcom_backend/triggerer.py
gs_xcom_backend_triggerer-0.0.5.dist-info/METADATA
gs_xcom_backend_triggerer-0.0.5.dist-info/WHEEL
gs_xcom_backend_triggerer-0.0.5.dist-info/top_level.txt
gs_xcom_backend_triggerer-0.0.5.dist-info/RECORD
