Metadata-Version: 2.1
Name: gs-xcom-backend-triggerer
Version: 0.0.5
Summary: triggerer gs_xcom_backend module file
Author: imvj202
Author-email: imvj202@gmail.com
Classifier: Development Status :: 1 - Planning
Classifier: Intended Audience :: Developers
Classifier: Programming Language :: Python :: 3
Classifier: Operating System :: Unix
Classifier: Operating System :: MacOS :: MacOS X
Classifier: Operating System :: Microsoft :: Windows
